toss_pyozzi_commons/__init__.py
pyozzi_test-999.9.22.dist-info/METADATA
pyozzi_test-999.9.22.dist-info/WHEEL
pyozzi_test-999.9.22.dist-info/top_level.txt
pyozzi_test-999.9.22.dist-info/RECORD
