Metadata-Version: 2.1
Name: pyozzi-test
Version: 999.9.22
Summary: test library
Home-page: https://github.com/pyozzi
Author: pyozzi
Author-email: pyozzi@toss.im
Classifier: Programming Language :: Python :: 3
Classifier: License :: OSI Approved :: MIT License
Classifier: Operating System :: OS Independent
Requires-Python: >=3.6
